seleniumeasy/__init__.py
seleniumeasy/main.py
seleniumeasy/update.py
seleniumeasy-0.1.2.dist-info/METADATA
seleniumeasy-0.1.2.dist-info/WHEEL
seleniumeasy-0.1.2.dist-info/top_level.txt
seleniumeasy-0.1.2.dist-info/RECORD
