Metadata-Version: 2.1
Name: seleniumeasy
Version: 0.1.2
Requires-Dist: pandas>=2.2.3
Requires-Dist: requests>=2.32.3
Requires-Dist: bs4>=0.0.2
Requires-Dist: selenium>=4.29.0
Requires-Dist: lxml>=5.3.1
